chaff_physics/__init__.py
chaff_physics/batch.py
chaff_physics/contaminate.py
chaff_physics/extract.py
chaff_physics/fingerprint.py
chaff_physics/make_dockopt_ready.py
chaff_physics/random_split.py
chaff_physics/split_db2.py
chaff_physics/yaml_wrangler.py
chaff_tools-0.0.1.dist-info/METADATA
chaff_tools-0.0.1.dist-info/WHEEL
chaff_tools-0.0.1.dist-info/entry_points.txt
chaff_tools-0.0.1.dist-info/top_level.txt
chaff_tools-0.0.1.dist-info/RECORD
