Metadata-Version: 2.4
Name: chaff-tools
Version: 0.0.1
Summary: Pipeline for contamination, calcuating raco-score, and assessing sensitivty of both physic-based and machine-learning models.
Home-page: https://github.com/maomlab/chaff-tools
Author: Hai Pham, Christopher Patsalis
Author-email: pha298392@gmail.com, patsalis@umich.edu
Classifier: Programming Language :: Python :: 3
Classifier: License :: OSI Approved :: MIT License
Classifier: Operating System :: OS Independent
Requires-Python: >=3.10
Requires-Dist: requests
Requires-Dist: python-dotenv
Requires-Dist: beautifulsoup4
Requires-Dist: numpy
Requires-Dist: pyyaml
Requires-Dist: pandas
Dynamic: author
Dynamic: author-email
Dynamic: classifier
Dynamic: description
Dynamic: description-content-type
Dynamic: home-page
Dynamic: requires-dist
Dynamic: requires-python
Dynamic: summary
